latexbuild/latex_parse.py
latexbuild/utils.py
latexbuild/assertions.py
latexbuild/subprocess_extension.py
latexbuild/jinja2_extension.py
latexbuild/__init__.py
latexbuild/build.py
latexbuild-0.2.2.dist-info/WHEEL
latexbuild-0.2.2.dist-info/RECORD
latexbuild-0.2.2.dist-info/METADATA
latexbuild-0.2.2.dist-info/DESCRIPTION.rst
latexbuild-0.2.2.dist-info/top_level.txt
latexbuild-0.2.2.dist-info/metadata.json
