Metadata-Version: 2.0
Name: latexbuild
Version: 0.2.2
Summary: Building Jinja2 templates with latex
Home-page: https://github.com/pappasam/latexbuild
Author: Samuel Roeca
Author-email: samuel.roeca@gmail.com
License: MIT
Keywords: latex jinja2 build html texlive
Platform: UNKNOWN
Classifier: Development Status :: 3 - Alpha
Classifier: Intended Audience :: Developers
Classifier: Topic :: Software Development :: Build Tools
Classifier: Topic :: Text Processing :: Markup :: LaTeX
Classifier: Topic :: Software Development :: Libraries :: Python Modules
Classifier: Topic :: Utilities
Classifier: License :: OSI Approved :: MIT License
Classifier: Natural Language :: English
Classifier: Operating System :: POSIX :: Linux
Classifier: Programming Language :: Python :: 3 :: Only
Requires-Dist: Jinja2 (>=2.8)
